{
    "custom_metrics": {},
    "episode_media": {},
    "info": {
        "learner": {
            "policy_0": {
                "learner_stats": {
                    "allreduce_latency": 0.0,
                    "grad_gnorm": 5.029346466064453,
                    "cur_kl_coeff": 0.3,
                    "cur_lr": 5e-05,
                    "total_loss": 7.600331287673026,
                    "policy_loss": -0.07529990838163278,
                    "vf_loss": 7.679142774235118,
                    "vf_explained_var": -0.08793653394236708,
                    "kl": 0.012280343035354052,
                    "entropy": 0.7195703991434791,
                    "entropy_coeff": 0.01
                },
                "model": {},
                "custom_metrics": {},
                "num_agent_steps_trained": 121.0909090909091,
                "num_grad_updates_lifetime": 38115.5,
                "diff_num_grad_updates_vs_sampler_policy": 164.5
            },
            "policy_1": {
                "learner_stats": {
                    "allreduce_latency": 0.0,
                    "grad_gnorm": 1.7179752588272095,
                    "cur_kl_coeff": 0.19999999999999996,
                    "cur_lr": 5e-05,
                    "total_loss": 9.781676436915543,
                    "policy_loss": -0.0838995951626478,
                    "vf_loss": 9.923864957058068,
                    "vf_explained_var": 0.11565638040051315,
                    "kl": 0.01482775411219061,
                    "entropy": 1.2250886111548454,
                    "entropy_coeff": 0.04999999999999999
                },
                "model": {},
                "custom_metrics": {},
                "num_agent_steps_trained": 121.63636363636364,
                "num_grad_updates_lifetime": 38115.5,
                "diff_num_grad_updates_vs_sampler_policy": 164.5
            },
            "policy_2": {
                "learner_stats": {
                    "allreduce_latency": 0.0,
                    "grad_gnorm": 2.308373212814331,
                    "cur_kl_coeff": 0.19999999999999996,
                    "cur_lr": 5e-05,
                    "total_loss": 8.480122274341005,
                    "policy_loss": -0.0787963220906077,
                    "vf_loss": 8.694633466547186,
                    "vf_explained_var": -0.006438918547196822,
                    "kl": 0.011297561554342488,
                    "entropy": 1.3797437512513362,
                    "entropy_coeff": 0.09999999999999998
                },
                "model": {},
                "custom_metrics": {},
                "num_agent_steps_trained": 120.9090909090909,
                "num_grad_updates_lifetime": 38115.5,
                "diff_num_grad_updates_vs_sampler_policy": 164.5
            }
        },
        "num_env_steps_sampled": 464000,
        "num_env_steps_trained": 464000,
        "num_agent_steps_sampled": 463998,
        "num_agent_steps_trained": 463998
    },
    "env_runners": {
        "episode_reward_max": -169.0,
        "episode_reward_min": -595.0,
        "episode_reward_mean": -410.69,
        "episode_len_mean": 386.52,
        "episode_media": {},
        "episodes_timesteps_total": 38652,
        "policy_reward_min": {
            "policy_1": -360.0,
            "policy_2": -405.0,
            "policy_0": -370.0
        },
        "policy_reward_max": {
            "policy_1": -15.0,
            "policy_2": -22.0,
            "policy_0": -9.0
        },
        "policy_reward_mean": {
            "policy_1": -134.34,
            "policy_2": -155.24,
            "policy_0": -121.11
        },
        "custom_metrics": {},
        "hist_stats": {
            "episode_reward": [
                -455.0,
                -384.0,
                -485.0,
                -446.0,
                -430.0,
                -396.0,
                -486.0,
                -329.0,
                -422.0,
                -485.0,
                -289.0,
                -546.0,
                -427.0,
                -547.0,
                -450.0,
                -303.0,
                -439.0,
                -288.0,
                -419.0,
                -486.0,
                -409.0,
                -265.0,
                -383.0,
                -400.0,
                -366.0,
                -496.0,
                -289.0,
                -532.0,
                -425.0,
                -299.0,
                -554.0,
                -477.0,
                -546.0,
                -396.0,
                -361.0,
                -347.0,
                -488.0,
                -308.0,
                -509.0,
                -402.0,
                -337.0,
                -364.0,
                -346.0,
                -459.0,
                -444.0,
                -492.0,
                -449.0,
                -434.0,
                -452.0,
                -518.0,
                -335.0,
                -381.0,
                -533.0,
                -511.0,
                -341.0,
                -375.0,
                -273.0,
                -399.0,
                -239.0,
                -512.0,
                -515.0,
                -358.0,
                -373.0,
                -393.0,
                -363.0,
                -423.0,
                -411.0,
                -349.0,
                -444.0,
                -335.0,
                -423.0,
                -510.0,
                -521.0,
                -420.0,
                -496.0,
                -471.0,
                -318.0,
                -339.0,
                -446.0,
                -373.0,
                -445.0,
                -595.0,
                -463.0,
                -235.0,
                -169.0,
                -440.0,
                -471.0,
                -310.0,
                -487.0,
                -355.0,
                -403.0,
                -415.0,
                -357.0,
                -355.0,
                -481.0,
                -425.0,
                -261.0,
                -430.0,
                -306.0,
                -427.0
            ],
            "episode_lengths": [
                864,
                468,
                612,
                142,
                120,
                104,
                170,
                924,
                584,
                962,
                144,
                128,
                206,
                332,
                218,
                148,
                274,
                1186,
                302,
                268,
                190,
                376,
                750,
                472,
                552,
                298,
                76,
                194,
                92,
                114,
                356,
                440,
                232,
                112,
                1854,
                956,
                204,
                188,
                162,
                226,
                364,
                500,
                548,
                442,
                260,
                184,
                1432,
                212,
                954,
                102,
                200,
                584,
                284,
                126,
                486,
                304,
                542,
                142,
                1150,
                260,
                966,
                142,
                232,
                230,
                616,
                198,
                340,
                464,
                122,
                560,
                1110,
                662,
                218,
                334,
                192,
                176,
                130,
                240,
                146,
                130,
                644,
                716,
                358,
                152,
                1184,
                102,
                388,
                90,
                104,
                334,
                92,
                762,
                110,
                94,
                72,
                468,
                206,
                104,
                278,
                110
            ],
            "policy_policy_1_reward": [
                -310.0,
                -99.0,
                -330.0,
                -147.0,
                -174.0,
                -21.0,
                -52.0,
                -19.0,
                -105.0,
                -108.0,
                -39.0,
                -56.0,
                -117.0,
                -295.0,
                -280.0,
                -29.0,
                -108.0,
                -145.0,
                -111.0,
                -54.0,
                -183.0,
                -81.0,
                -150.0,
                -37.0,
                -155.0,
                -84.0,
                -205.0,
                -300.0,
                -26.0,
                -25.0,
                -360.0,
                -138.0,
                -325.0,
                -29.0,
                -210.0,
                -171.0,
                -355.0,
                -47.0,
                -310.0,
                -177.0,
                -200.0,
                -145.0,
                -59.0,
                -225.0,
                -300.0,
                -174.0,
                -177.0,
                -44.0,
                -270.0,
                -34.0,
                -87.0,
                -30.0,
                -330.0,
                -87.0,
                -185.0,
                -93.0,
                -200.0,
                -26.0,
                -135.0,
                -231.0,
                -189.0,
                -30.0,
                -56.0,
                -265.0,
                -43.0,
                -138.0,
                -15.0,
                -225.0,
                -53.0,
                -185.0,
                -255.0,
                -360.0,
                -57.0,
                -265.0,
                -62.0,
                -45.0,
                -24.0,
                -35.0,
                -29.0,
                -27.0,
                -46.0,
                -174.0,
                -186.0,
                -45.0,
                -105.0,
                -29.0,
                -315.0,
                -37.0,
                -43.0,
                -205.0,
                -44.0,
                -280.0,
                -36.0,
                -25.0,
                -41.0,
                -220.0,
                -35.0,
                -67.0,
                -108.0,
                -36.0
            ],
            "policy_policy_2_reward": [
                -120.0,
                -50.0,
                -114.0,
                -49.0,
                -41.0,
                -315.0,
                -320.0,
                -250.0,
                -22.0,
                -67.0,
                -205.0,
                -310.0,
                -35.0,
                -192.0,
                -147.0,
                -250.0,
                -46.0,
                -99.0,
                -43.0,
                -210.0,
                -56.0,
                -24.0,
                -33.0,
                -180.0,
                -165.0,
                -42.0,
                -54.0,
                -192.0,
                -300.0,
                -235.0,
                -165.0,
                -59.0,
                -165.0,
                -205.0,
                -126.0,
                -51.0,
                -105.0,
                -240.0,
                -165.0,
                -40.0,
                -114.0,
                -177.0,
                -200.0,
                -162.0,
                -114.0,
                -53.0,
                -47.0,
                -285.0,
                -147.0,
                -325.0,
                -63.0,
                -270.0,
                -126.0,
                -64.0,
                -120.0,
                -52.0,
                -30.0,
                -325.0,
                -75.0,
                -61.0,
                -51.0,
                -175.0,
                -200.0,
                -90.0,
                -185.0,
                -60.0,
                -51.0,
                -75.0,
                -265.0,
                -132.0,
                -126.0,
                -123.0,
                -365.0,
                -126.0,
                -305.0,
                -300.0,
                -240.0,
                -295.0,
                -270.0,
                -250.0,
                -195.0,
                -56.0,
                -57.0,
                -130.0,
                -45.0,
                -255.0,
                -132.0,
                -165.0,
                -405.0,
                -99.0,
                -245.0,
                -99.0,
                -195.0,
                -255.0,
                -305.0,
                -162.0,
                -160.0,
                -315.0,
                -63.0,
                -205.0
            ],
            "policy_policy_0_reward": [
                -25.0,
                -235.0,
                -41.0,
                -250.0,
                -215.0,
                -60.0,
                -114.0,
                -60.0,
                -295.0,
                -310.0,
                -45.0,
                -180.0,
                -275.0,
                -60.0,
                -23.0,
                -24.0,
                -285.0,
                -44.0,
                -265.0,
                -222.0,
                -170.0,
                -160.0,
                -200.0,
                -183.0,
                -46.0,
                -370.0,
                -30.0,
                -40.0,
                -99.0,
                -39.0,
                -29.0,
                -280.0,
                -56.0,
                -162.0,
                -25.0,
                -125.0,
                -28.0,
                -21.0,
                -34.0,
                -185.0,
                -23.0,
                -42.0,
                -87.0,
                -72.0,
                -30.0,
                -265.0,
                -225.0,
                -105.0,
                -35.0,
                -159.0,
                -185.0,
                -81.0,
                -77.0,
                -360.0,
                -36.0,
                -230.0,
                -43.0,
                -48.0,
                -29.0,
                -220.0,
                -275.0,
                -153.0,
                -117.0,
                -38.0,
                -135.0,
                -225.0,
                -345.0,
                -49.0,
                -126.0,
                -18.0,
                -42.0,
                -27.0,
                -99.0,
                -29.0,
                -129.0,
                -126.0,
                -54.0,
                -9.0,
                -147.0,
                -96.0,
                -204.0,
                -365.0,
                -220.0,
                -60.0,
                -19.0,
                -156.0,
                -24.0,
                -108.0,
                -39.0,
                -51.0,
                -114.0,
                -36.0,
                -126.0,
                -75.0,
                -135.0,
                -43.0,
                -66.0,
                -48.0,
                -135.0,
                -186.0
            ]
        },
        "sampler_perf": {
            "mean_raw_obs_processing_ms": 0.20422816042648287,
            "mean_inference_ms": 0.756306231192621,
            "mean_action_processing_ms": 0.07069151691110842,
            "mean_env_wait_ms": 0.18259850835634922,
            "mean_env_render_ms": 0.0
        },
        "num_faulty_episodes": 0,
        "connector_metrics": {
            "ObsPreprocessorConnector_ms": 0.01248494784037272,
            "StateBufferConnector_ms": 0.0027005672454833984,
            "ViewRequirementAgentConnector_ms": 0.06444557507832845
        },
        "num_episodes": 16,
        "episode_return_max": -169.0,
        "episode_return_min": -595.0,
        "episode_return_mean": -410.69,
        "episodes_this_iter": 16
    },
    "num_healthy_workers": 1,
    "num_in_flight_async_sample_reqs": 0,
    "num_remote_worker_restarts": 0,
    "num_agent_steps_sampled": 463998,
    "num_agent_steps_trained": 463998,
    "num_env_steps_sampled": 464000,
    "num_env_steps_trained": 464000,
    "num_env_steps_sampled_this_iter": 4000,
    "num_env_steps_trained_this_iter": 4000,
    "num_env_steps_sampled_throughput_per_sec": 386.80703651893737,
    "num_env_steps_trained_throughput_per_sec": 386.80703651893737,
    "timesteps_total": 464000,
    "num_env_steps_sampled_lifetime": 464000,
    "num_agent_steps_sampled_lifetime": 463998,
    "num_steps_trained_this_iter": 4000,
    "agent_timesteps_total": 463998,
    "timers": {
        "training_iteration_time_ms": 10375.067,
        "restore_workers_time_ms": 0.01,
        "training_step_time_ms": 10375.039,
        "sample_time_ms": 4800.449,
        "learn_time_ms": 5570.162,
        "learn_throughput": 718.112,
        "synch_weights_time_ms": 4.234
    },
    "counters": {
        "num_env_steps_sampled": 464000,
        "num_env_steps_trained": 464000,
        "num_agent_steps_sampled": 463998,
        "num_agent_steps_trained": 463998
    },
    "done": false,
    "training_iteration": 116,
    "trial_id": "default",
    "date": "2024-12-14_14-00-57",
    "timestamp": 1734181257,
    "time_this_iter_s": 10.345882177352905,
    "time_total_s": 1208.3440566062927,
    "pid": 86490,
    "hostname": "GalacticRepublic",
    "node_ip": "192.168.0.236",
    "time_since_restore": 1208.3440566062927,
    "iterations_since_restore": 116,
    "perf": {
        "cpu_util_percent": 22.12,
        "ram_util_percent": 72.03333333333333
    }
}