{
    "custom_metrics": {},
    "episode_media": {},
    "info": {
        "learner": {
            "policy_0": {
                "learner_stats": {
                    "allreduce_latency": 0.0,
                    "grad_gnorm": 2.7295312881469727,
                    "cur_kl_coeff": 0.3,
                    "cur_lr": 5e-05,
                    "total_loss": 8.67577080148639,
                    "policy_loss": -0.07864758888767524,
                    "vf_loss": 8.756958704283743,
                    "vf_explained_var": 0.004855878605987086,
                    "kl": 0.015904145355663972,
                    "entropy": 0.7311588598020149,
                    "entropy_coeff": 0.01
                },
                "model": {},
                "custom_metrics": {},
                "num_agent_steps_trained": 120.9090909090909,
                "num_grad_updates_lifetime": 41415.5,
                "diff_num_grad_updates_vs_sampler_policy": 164.5
            },
            "policy_1": {
                "learner_stats": {
                    "allreduce_latency": 0.0,
                    "grad_gnorm": 2.536027669906616,
                    "cur_kl_coeff": 0.19999999999999996,
                    "cur_lr": 5e-05,
                    "total_loss": 8.98249112476002,
                    "policy_loss": -0.09048844574470863,
                    "vf_loss": 9.12998543219133,
                    "vf_explained_var": -0.06531660556793213,
                    "kl": 0.01643334328027281,
                    "entropy": 1.2058494728623015,
                    "entropy_coeff": 0.04999999999999999
                },
                "model": {},
                "custom_metrics": {},
                "num_agent_steps_trained": 121.54545454545455,
                "num_grad_updates_lifetime": 41415.5,
                "diff_num_grad_updates_vs_sampler_policy": 164.5
            },
            "policy_2": {
                "learner_stats": {
                    "allreduce_latency": 0.0,
                    "grad_gnorm": 2.63826060295105,
                    "cur_kl_coeff": 0.19999999999999996,
                    "cur_lr": 5e-05,
                    "total_loss": 8.712588188864968,
                    "policy_loss": -0.08734403882600887,
                    "vf_loss": 8.936669994123054,
                    "vf_explained_var": -0.002266748746236165,
                    "kl": 0.015321267627108321,
                    "entropy": 1.3980203740524524,
                    "entropy_coeff": 0.09999999999999998
                },
                "model": {},
                "custom_metrics": {},
                "num_agent_steps_trained": 121.18181818181819,
                "num_grad_updates_lifetime": 41415.5,
                "diff_num_grad_updates_vs_sampler_policy": 164.5
            }
        },
        "num_env_steps_sampled": 504000,
        "num_env_steps_trained": 504000,
        "num_agent_steps_sampled": 503998,
        "num_agent_steps_trained": 503998
    },
    "env_runners": {
        "episode_reward_max": -203.0,
        "episode_reward_min": -654.0,
        "episode_reward_mean": -414.8,
        "episode_len_mean": 392.72,
        "episode_media": {},
        "episodes_timesteps_total": 39272,
        "policy_reward_min": {
            "policy_0": -370.0,
            "policy_1": -395.0,
            "policy_2": -420.0
        },
        "policy_reward_max": {
            "policy_0": -6.0,
            "policy_1": -9.0,
            "policy_2": -21.0
        },
        "policy_reward_mean": {
            "policy_0": -114.94,
            "policy_1": -130.52,
            "policy_2": -169.34
        },
        "custom_metrics": {},
        "hist_stats": {
            "episode_reward": [
                -385.0,
                -338.0,
                -397.0,
                -405.0,
                -383.0,
                -463.0,
                -291.0,
                -502.0,
                -555.0,
                -228.0,
                -533.0,
                -486.0,
                -476.0,
                -353.0,
                -280.0,
                -469.0,
                -441.0,
                -434.0,
                -448.0,
                -445.0,
                -329.0,
                -261.0,
                -273.0,
                -418.0,
                -336.0,
                -417.0,
                -430.0,
                -396.0,
                -437.0,
                -335.0,
                -509.0,
                -402.0,
                -350.0,
                -350.0,
                -385.0,
                -391.0,
                -429.0,
                -406.0,
                -478.0,
                -379.0,
                -492.0,
                -459.0,
                -270.0,
                -310.0,
                -431.0,
                -426.0,
                -323.0,
                -325.0,
                -409.0,
                -654.0,
                -480.0,
                -423.0,
                -373.0,
                -593.0,
                -483.0,
                -392.0,
                -392.0,
                -297.0,
                -391.0,
                -376.0,
                -413.0,
                -430.0,
                -443.0,
                -411.0,
                -501.0,
                -289.0,
                -485.0,
                -390.0,
                -466.0,
                -342.0,
                -482.0,
                -250.0,
                -583.0,
                -522.0,
                -378.0,
                -423.0,
                -573.0,
                -509.0,
                -391.0,
                -507.0,
                -203.0,
                -497.0,
                -313.0,
                -349.0,
                -336.0,
                -376.0,
                -261.0,
                -491.0,
                -563.0,
                -561.0,
                -365.0,
                -279.0,
                -478.0,
                -468.0,
                -547.0,
                -521.0,
                -382.0,
                -531.0,
                -354.0,
                -495.0
            ],
            "episode_lengths": [
                100,
                146,
                704,
                136,
                860,
                198,
                410,
                568,
                622,
                1140,
                782,
                1402,
                974,
                982,
                166,
                430,
                154,
                368,
                126,
                192,
                598,
                360,
                194,
                326,
                190,
                152,
                246,
                258,
                384,
                878,
                190,
                376,
                374,
                634,
                156,
                188,
                204,
                118,
                96,
                282,
                350,
                1022,
                214,
                210,
                714,
                196,
                360,
                490,
                104,
                108,
                150,
                408,
                494,
                116,
                180,
                180,
                960,
                2196,
                190,
                1442,
                612,
                220,
                188,
                164,
                174,
                174,
                168,
                706,
                80,
                164,
                880,
                378,
                234,
                346,
                832,
                204,
                156,
                166,
                296,
                112,
                176,
                112,
                340,
                1182,
                674,
                324,
                202,
                518,
                330,
                200,
                692,
                152,
                130,
                222,
                150,
                136,
                150,
                154,
                96,
                330
            ],
            "policy_policy_0_reward": [
                -171.0,
                -156.0,
                -32.0,
                -135.0,
                -111.0,
                -171.0,
                -145.0,
                -270.0,
                -99.0,
                -45.0,
                -370.0,
                -23.0,
                -63.0,
                -41.0,
                -99.0,
                -215.0,
                -186.0,
                -220.0,
                -205.0,
                -49.0,
                -16.0,
                -48.0,
                -84.0,
                -185.0,
                -120.0,
                -36.0,
                -147.0,
                -185.0,
                -22.0,
                -48.0,
                -171.0,
                -67.0,
                -39.0,
                -33.0,
                -180.0,
                -45.0,
                -57.0,
                -81.0,
                -310.0,
                -16.0,
                -35.0,
                -24.0,
                -90.0,
                -190.0,
                -31.0,
                -21.0,
                -26.0,
                -44.0,
                -144.0,
                -162.0,
                -43.0,
                -216.0,
                -185.0,
                -63.0,
                -135.0,
                -99.0,
                -225.0,
                -28.0,
                -153.0,
                -111.0,
                -108.0,
                -96.0,
                -69.0,
                -15.0,
                -67.0,
                -63.0,
                -114.0,
                -61.0,
                -81.0,
                -63.0,
                -35.0,
                -43.0,
                -126.0,
                -6.0,
                -99.0,
                -147.0,
                -132.0,
                -290.0,
                -220.0,
                -153.0,
                -45.0,
                -174.0,
                -53.0,
                -180.0,
                -35.0,
                -17.0,
                -185.0,
                -123.0,
                -315.0,
                -305.0,
                -144.0,
                -60.0,
                -58.0,
                -17.0,
                -204.0,
                -210.0,
                -54.0,
                -305.0,
                -36.0,
                -265.0
            ],
            "policy_policy_1_reward": [
                -34.0,
                -57.0,
                -245.0,
                -10.0,
                -67.0,
                -52.0,
                -96.0,
                -183.0,
                -41.0,
                -105.0,
                -120.0,
                -340.0,
                -260.0,
                -195.0,
                -41.0,
                -222.0,
                -30.0,
                -156.0,
                -201.0,
                -225.0,
                -265.0,
                -135.0,
                -9.0,
                -165.0,
                -141.0,
                -225.0,
                -43.0,
                -165.0,
                -250.0,
                -47.0,
                -43.0,
                -200.0,
                -230.0,
                -155.0,
                -159.0,
                -250.0,
                -22.0,
                -40.0,
                -111.0,
                -225.0,
                -295.0,
                -285.0,
                -40.0,
                -99.0,
                -235.0,
                -285.0,
                -195.0,
                -170.0,
                -30.0,
                -77.0,
                -155.0,
                -87.0,
                -141.0,
                -395.0,
                -58.0,
                -38.0,
                -120.0,
                -140.0,
                -43.0,
                -20.0,
                -40.0,
                -9.0,
                -44.0,
                -46.0,
                -290.0,
                -41.0,
                -66.0,
                -200.0,
                -35.0,
                -39.0,
                -330.0,
                -120.0,
                -37.0,
                -390.0,
                -29.0,
                -81.0,
                -66.0,
                -180.0,
                -129.0,
                -44.0,
                -63.0,
                -38.0,
                -125.0,
                -135.0,
                -130.0,
                -215.0,
                -48.0,
                -43.0,
                -189.0,
                -210.0,
                -31.0,
                -44.0,
                -270.0,
                -310.0,
                -53.0,
                -61.0,
                -23.0,
                -165.0,
                -53.0,
                -162.0
            ],
            "policy_policy_2_reward": [
                -180.0,
                -125.0,
                -120.0,
                -260.0,
                -205.0,
                -240.0,
                -50.0,
                -49.0,
                -415.0,
                -78.0,
                -43.0,
                -123.0,
                -153.0,
                -117.0,
                -140.0,
                -32.0,
                -225.0,
                -58.0,
                -42.0,
                -171.0,
                -48.0,
                -78.0,
                -180.0,
                -68.0,
                -75.0,
                -156.0,
                -240.0,
                -46.0,
                -165.0,
                -240.0,
                -295.0,
                -135.0,
                -81.0,
                -162.0,
                -46.0,
                -96.0,
                -350.0,
                -285.0,
                -57.0,
                -138.0,
                -162.0,
                -150.0,
                -140.0,
                -21.0,
                -165.0,
                -120.0,
                -102.0,
                -111.0,
                -235.0,
                -415.0,
                -282.0,
                -120.0,
                -47.0,
                -135.0,
                -290.0,
                -255.0,
                -47.0,
                -129.0,
                -195.0,
                -245.0,
                -265.0,
                -325.0,
                -330.0,
                -350.0,
                -144.0,
                -185.0,
                -305.0,
                -129.0,
                -350.0,
                -240.0,
                -117.0,
                -87.0,
                -420.0,
                -126.0,
                -250.0,
                -195.0,
                -375.0,
                -39.0,
                -42.0,
                -310.0,
                -95.0,
                -285.0,
                -135.0,
                -34.0,
                -171.0,
                -144.0,
                -28.0,
                -325.0,
                -59.0,
                -46.0,
                -190.0,
                -175.0,
                -150.0,
                -141.0,
                -290.0,
                -250.0,
                -305.0,
                -61.0,
                -265.0,
                -68.0
            ]
        },
        "sampler_perf": {
            "mean_raw_obs_processing_ms": 0.20416761545793513,
            "mean_inference_ms": 0.7561433431113739,
            "mean_action_processing_ms": 0.07071451484015856,
            "mean_env_wait_ms": 0.18188482935091074,
            "mean_env_render_ms": 0.0
        },
        "num_faulty_episodes": 0,
        "connector_metrics": {
            "ObsPreprocessorConnector_ms": 0.01229556401570638,
            "StateBufferConnector_ms": 0.002750237782796224,
            "ViewRequirementAgentConnector_ms": 0.06474836667378743
        },
        "num_episodes": 13,
        "episode_return_max": -203.0,
        "episode_return_min": -654.0,
        "episode_return_mean": -414.8,
        "episodes_this_iter": 13
    },
    "num_healthy_workers": 1,
    "num_in_flight_async_sample_reqs": 0,
    "num_remote_worker_restarts": 0,
    "num_agent_steps_sampled": 503998,
    "num_agent_steps_trained": 503998,
    "num_env_steps_sampled": 504000,
    "num_env_steps_trained": 504000,
    "num_env_steps_sampled_this_iter": 4000,
    "num_env_steps_trained_this_iter": 4000,
    "num_env_steps_sampled_throughput_per_sec": 384.2853525145686,
    "num_env_steps_trained_throughput_per_sec": 384.2853525145686,
    "timesteps_total": 504000,
    "num_env_steps_sampled_lifetime": 504000,
    "num_agent_steps_sampled_lifetime": 503998,
    "num_steps_trained_this_iter": 4000,
    "agent_timesteps_total": 503998,
    "timers": {
        "training_iteration_time_ms": 10530.988,
        "restore_workers_time_ms": 0.01,
        "training_step_time_ms": 10530.962,
        "sample_time_ms": 4857.14,
        "learn_time_ms": 5669.189,
        "learn_throughput": 705.568,
        "synch_weights_time_ms": 4.428
    },
    "counters": {
        "num_env_steps_sampled": 504000,
        "num_env_steps_trained": 504000,
        "num_agent_steps_sampled": 503998,
        "num_agent_steps_trained": 503998
    },
    "done": false,
    "training_iteration": 126,
    "trial_id": "default",
    "date": "2024-12-14_14-02-43",
    "timestamp": 1734181363,
    "time_this_iter_s": 10.414370059967041,
    "time_total_s": 1313.7015726566315,
    "pid": 86490,
    "hostname": "GalacticRepublic",
    "node_ip": "192.168.0.236",
    "time_since_restore": 1313.7015726566315,
    "iterations_since_restore": 126,
    "perf": {
        "cpu_util_percent": 21.8,
        "ram_util_percent": 72.21333333333334
    }
}