{
    "custom_metrics": {},
    "episode_media": {},
    "info": {
        "learner": {
            "policy_1": {
                "learner_stats": {
                    "allreduce_latency": 0.0,
                    "grad_gnorm": 1.3039913177490234,
                    "cur_kl_coeff": 0.09999999999999998,
                    "cur_lr": 5e-05,
                    "total_loss": 9.080261952949293,
                    "policy_loss": -0.0937891048224022,
                    "vf_loss": 9.9622727394104,
                    "vf_explained_var": 0.00016201969349023066,
                    "kl": 0.013580424559043899,
                    "entropy": 1.5791593165108653,
                    "entropy_coeff": 0.5
                },
                "model": {},
                "custom_metrics": {},
                "num_agent_steps_trained": 120.9090909090909,
                "num_grad_updates_lifetime": 214665.5,
                "diff_num_grad_updates_vs_sampler_policy": 164.5
            },
            "policy_2": {
                "learner_stats": {
                    "allreduce_latency": 0.0,
                    "grad_gnorm": 1.1629996299743652,
                    "cur_kl_coeff": 0.04999999999999999,
                    "cur_lr": 5e-05,
                    "total_loss": 8.240938140406753,
                    "policy_loss": -0.0866683625672577,
                    "vf_loss": 9.947522102702747,
                    "vf_explained_var": 5.7912053483905215e-05,
                    "kl": 0.011600221129395747,
                    "entropy": 1.6204956415927771,
                    "entropy_coeff": 1.0
                },
                "model": {},
                "custom_metrics": {},
                "num_agent_steps_trained": 120.72727272727273,
                "num_grad_updates_lifetime": 214665.5,
                "diff_num_grad_updates_vs_sampler_policy": 164.5
            },
            "policy_0": {
                "learner_stats": {
                    "allreduce_latency": 0.0,
                    "grad_gnorm": 3.727806568145752,
                    "cur_kl_coeff": 0.19999999999999996,
                    "cur_lr": 5e-05,
                    "total_loss": 7.667809466159705,
                    "policy_loss": -0.10484722925237182,
                    "vf_loss": 7.893065920743076,
                    "vf_explained_var": 0.008374463066910252,
                    "kl": 0.015023896542718128,
                    "entropy": 1.234140398646846,
                    "entropy_coeff": 0.09999999999999998
                },
                "model": {},
                "custom_metrics": {},
                "num_agent_steps_trained": 122.0,
                "num_grad_updates_lifetime": 214665.5,
                "diff_num_grad_updates_vs_sampler_policy": 164.5
            }
        },
        "num_env_steps_sampled": 2604000,
        "num_env_steps_trained": 2604000,
        "num_agent_steps_sampled": 2603998,
        "num_agent_steps_trained": 2603998
    },
    "env_runners": {
        "episode_reward_max": -219.0,
        "episode_reward_min": -659.0,
        "episode_reward_mean": -444.45,
        "episode_len_mean": 143.98,
        "episode_media": {},
        "episodes_timesteps_total": 14398,
        "policy_reward_min": {
            "policy_0": -360.0,
            "policy_1": -405.0,
            "policy_2": -425.0
        },
        "policy_reward_max": {
            "policy_0": -8.0,
            "policy_1": -27.0,
            "policy_2": -41.0
        },
        "policy_reward_mean": {
            "policy_0": -88.62,
            "policy_1": -161.15,
            "policy_2": -194.68
        },
        "custom_metrics": {},
        "hist_stats": {
            "episode_reward": [
                -219.0,
                -415.0,
                -509.0,
                -553.0,
                -548.0,
                -437.0,
                -387.0,
                -519.0,
                -551.0,
                -423.0,
                -346.0,
                -441.0,
                -353.0,
                -557.0,
                -434.0,
                -526.0,
                -460.0,
                -329.0,
                -251.0,
                -252.0,
                -412.0,
                -565.0,
                -374.0,
                -421.0,
                -544.0,
                -355.0,
                -409.0,
                -551.0,
                -516.0,
                -313.0,
                -611.0,
                -524.0,
                -509.0,
                -528.0,
                -325.0,
                -488.0,
                -358.0,
                -390.0,
                -447.0,
                -442.0,
                -395.0,
                -415.0,
                -425.0,
                -506.0,
                -535.0,
                -394.0,
                -515.0,
                -457.0,
                -343.0,
                -520.0,
                -378.0,
                -371.0,
                -460.0,
                -444.0,
                -442.0,
                -531.0,
                -464.0,
                -476.0,
                -431.0,
                -576.0,
                -432.0,
                -465.0,
                -348.0,
                -493.0,
                -439.0,
                -497.0,
                -369.0,
                -340.0,
                -383.0,
                -414.0,
                -407.0,
                -645.0,
                -659.0,
                -475.0,
                -527.0,
                -358.0,
                -472.0,
                -331.0,
                -432.0,
                -427.0,
                -357.0,
                -451.0,
                -403.0,
                -491.0,
                -419.0,
                -363.0,
                -495.0,
                -504.0,
                -522.0,
                -457.0,
                -382.0,
                -344.0,
                -593.0,
                -449.0,
                -481.0,
                -409.0,
                -436.0,
                -381.0,
                -463.0,
                -462.0
            ],
            "episode_lengths": [
                178,
                154,
                148,
                130,
                128,
                148,
                136,
                182,
                178,
                206,
                132,
                90,
                124,
                136,
                114,
                214,
                94,
                168,
                186,
                246,
                152,
                124,
                152,
                136,
                116,
                142,
                172,
                148,
                148,
                132,
                150,
                98,
                122,
                172,
                116,
                148,
                84,
                136,
                144,
                80,
                100,
                120,
                140,
                118,
                140,
                94,
                104,
                216,
                170,
                162,
                112,
                160,
                198,
                226,
                178,
                132,
                188,
                206,
                150,
                122,
                118,
                116,
                120,
                128,
                158,
                128,
                102,
                156,
                130,
                226,
                204,
                136,
                100,
                126,
                114,
                160,
                114,
                136,
                120,
                202,
                154,
                90,
                100,
                160,
                104,
                232,
                156,
                268,
                120,
                106,
                152,
                112,
                120,
                176,
                116,
                156,
                96,
                158,
                116,
                112
            ],
            "policy_policy_0_reward": [
                -30.0,
                -72.0,
                -29.0,
                -51.0,
                -165.0,
                -156.0,
                -51.0,
                -290.0,
                -37.0,
                -45.0,
                -125.0,
                -99.0,
                -129.0,
                -13.0,
                -96.0,
                -62.0,
                -78.0,
                -120.0,
                -63.0,
                -33.0,
                -54.0,
                -156.0,
                -114.0,
                -18.0,
                -37.0,
                -54.0,
                -93.0,
                -310.0,
                -11.0,
                -8.0,
                -29.0,
                -46.0,
                -150.0,
                -20.0,
                -72.0,
                -290.0,
                -93.0,
                -180.0,
                -64.0,
                -52.0,
                -42.0,
                -60.0,
                -171.0,
                -21.0,
                -20.0,
                -24.0,
                -162.0,
                -22.0,
                -12.0,
                -156.0,
                -78.0,
                -57.0,
                -34.0,
                -123.0,
                -59.0,
                -45.0,
                -225.0,
                -21.0,
                -20.0,
                -99.0,
                -69.0,
                -62.0,
                -41.0,
                -51.0,
                -51.0,
                -93.0,
                -135.0,
                -87.0,
                -87.0,
                -48.0,
                -13.0,
                -43.0,
                -360.0,
                -102.0,
                -57.0,
                -53.0,
                -153.0,
                -87.0,
                -90.0,
                -46.0,
                -54.0,
                -219.0,
                -230.0,
                -40.0,
                -46.0,
                -31.0,
                -24.0,
                -174.0,
                -138.0,
                -165.0,
                -34.0,
                -132.0,
                -33.0,
                -22.0,
                -123.0,
                -51.0,
                -270.0,
                -195.0,
                -35.0,
                -72.0
            ],
            "policy_policy_1_reward": [
                -74.0,
                -58.0,
                -285.0,
                -340.0,
                -63.0,
                -61.0,
                -56.0,
                -183.0,
                -310.0,
                -73.0,
                -180.0,
                -52.0,
                -49.0,
                -385.0,
                -43.0,
                -260.0,
                -27.0,
                -49.0,
                -38.0,
                -74.0,
                -58.0,
                -64.0,
                -80.0,
                -220.0,
                -330.0,
                -66.0,
                -71.0,
                -189.0,
                -310.0,
                -155.0,
                -405.0,
                -370.0,
                -59.0,
                -355.0,
                -53.0,
                -150.0,
                -45.0,
                -50.0,
                -245.0,
                -270.0,
                -43.0,
                -50.0,
                -34.0,
                -350.0,
                -320.0,
                -205.0,
                -33.0,
                -285.0,
                -220.0,
                -49.0,
                -65.0,
                -34.0,
                -315.0,
                -36.0,
                -230.0,
                -360.0,
                -183.0,
                -335.0,
                -270.0,
                -52.0,
                -73.0,
                -250.0,
                -145.0,
                -265.0,
                -265.0,
                -84.0,
                -49.0,
                -83.0,
                -51.0,
                -150.0,
                -235.0,
                -395.0,
                -252.0,
                -48.0,
                -380.0,
                -185.0,
                -74.0,
                -49.0,
                -72.0,
                -225.0,
                -58.0,
                -27.0,
                -129.0,
                -235.0,
                -235.0,
                -170.0,
                -315.0,
                -75.0,
                -54.0,
                -62.0,
                -270.0,
                -57.0,
                -365.0,
                -325.0,
                -58.0,
                -68.0,
                -111.0,
                -132.0,
                -290.0,
                -75.0
            ],
            "policy_policy_2_reward": [
                -115.0,
                -285.0,
                -195.0,
                -162.0,
                -320.0,
                -220.0,
                -280.0,
                -46.0,
                -204.0,
                -305.0,
                -41.0,
                -290.0,
                -175.0,
                -159.0,
                -295.0,
                -204.0,
                -355.0,
                -160.0,
                -150.0,
                -145.0,
                -300.0,
                -345.0,
                -180.0,
                -183.0,
                -177.0,
                -235.0,
                -245.0,
                -52.0,
                -195.0,
                -150.0,
                -177.0,
                -108.0,
                -300.0,
                -153.0,
                -200.0,
                -48.0,
                -220.0,
                -160.0,
                -138.0,
                -120.0,
                -310.0,
                -305.0,
                -220.0,
                -135.0,
                -195.0,
                -165.0,
                -320.0,
                -150.0,
                -111.0,
                -315.0,
                -235.0,
                -280.0,
                -111.0,
                -285.0,
                -153.0,
                -126.0,
                -56.0,
                -120.0,
                -141.0,
                -425.0,
                -290.0,
                -153.0,
                -162.0,
                -177.0,
                -123.0,
                -320.0,
                -185.0,
                -170.0,
                -245.0,
                -216.0,
                -159.0,
                -207.0,
                -47.0,
                -325.0,
                -90.0,
                -120.0,
                -245.0,
                -195.0,
                -270.0,
                -156.0,
                -245.0,
                -205.0,
                -44.0,
                -216.0,
                -138.0,
                -162.0,
                -156.0,
                -255.0,
                -330.0,
                -230.0,
                -78.0,
                -155.0,
                -195.0,
                -102.0,
                -300.0,
                -290.0,
                -55.0,
                -54.0,
                -138.0,
                -315.0
            ]
        },
        "sampler_perf": {
            "mean_raw_obs_processing_ms": 0.20941299086756515,
            "mean_inference_ms": 0.7508326626176762,
            "mean_action_processing_ms": 0.06867725243003975,
            "mean_env_wait_ms": 0.17258493981310197,
            "mean_env_render_ms": 0.0
        },
        "num_faulty_episodes": 0,
        "connector_metrics": {
            "ObsPreprocessorConnector_ms": 0.012210845947265625,
            "StateBufferConnector_ms": 0.0025385220845540366,
            "ViewRequirementAgentConnector_ms": 0.06097602844238281
        },
        "num_episodes": 29,
        "episode_return_max": -219.0,
        "episode_return_min": -659.0,
        "episode_return_mean": -444.45,
        "episodes_this_iter": 29
    },
    "num_healthy_workers": 1,
    "num_in_flight_async_sample_reqs": 0,
    "num_remote_worker_restarts": 0,
    "num_agent_steps_sampled": 2603998,
    "num_agent_steps_trained": 2603998,
    "num_env_steps_sampled": 2604000,
    "num_env_steps_trained": 2604000,
    "num_env_steps_sampled_this_iter": 4000,
    "num_env_steps_trained_this_iter": 4000,
    "num_env_steps_sampled_throughput_per_sec": 422.9234516643312,
    "num_env_steps_trained_throughput_per_sec": 422.9234516643312,
    "timesteps_total": 2604000,
    "num_env_steps_sampled_lifetime": 2604000,
    "num_agent_steps_sampled_lifetime": 2603998,
    "num_steps_trained_this_iter": 4000,
    "agent_timesteps_total": 2603998,
    "timers": {
        "training_iteration_time_ms": 9852.951,
        "restore_workers_time_ms": 0.009,
        "training_step_time_ms": 9852.926,
        "sample_time_ms": 4656.79,
        "learn_time_ms": 5191.94,
        "learn_throughput": 770.425,
        "synch_weights_time_ms": 4.008
    },
    "counters": {
        "num_env_steps_sampled": 2604000,
        "num_env_steps_trained": 2604000,
        "num_agent_steps_sampled": 2603998,
        "num_agent_steps_trained": 2603998
    },
    "done": false,
    "training_iteration": 651,
    "trial_id": "default",
    "date": "2024-12-14_15-09-00",
    "timestamp": 1734185340,
    "time_this_iter_s": 9.463121891021729,
    "time_total_s": 6767.162983894348,
    "pid": 68637,
    "hostname": "GalacticRepublic",
    "node_ip": "192.168.0.236",
    "time_since_restore": 6767.162983894348,
    "iterations_since_restore": 651,
    "perf": {
        "cpu_util_percent": 20.392307692307693,
        "ram_util_percent": 73.13846153846154
    }
}